AUTHORS.rst
CHANGES.rst
LICENSE.txt
MANIFEST.in
README.rst
TODO.rst
setup.py
ajax_loading_overlay/__init__.py
ajax_loading_overlay/models.py
ajax_loading_overlay/tests.py
ajax_loading_overlay/static/ajax_loading_overlay/jquery.ajax-loading-overlay.js
django_ajax_loading_overlay.egg-info/PKG-INFO
django_ajax_loading_overlay.egg-info/SOURCES.txt
django_ajax_loading_overlay.egg-info/dependency_links.txt
django_ajax_loading_overlay.egg-info/not-zip-safe
django_ajax_loading_overlay.egg-info/top_level.txt