Metadata-Version: 1.0
Name: django-ajax-loading-overlay
Version: 0.1.2
Summary: Uses JS to add/remove a loading overlay during Ajax calls
Home-page: https://github.com/jgerigmeyer/django-ajax-loading-overlay/
Author: Jonny Gerig Meyer
Author-email: jonny@oddbird.net
License: UNKNOWN
Platform: UNKNOWN
Classifier: Development Status :: 3 - Alpha
Classifier: Environment :: Web Environment
Classifier: Intended Audience :: Developers
Classifier: License :: OSI Approved :: BSD License
Classifier: Operating System :: OS Independent
Classifier: Programming Language :: Python
Classifier: Programming Language :: Python :: 2
Classifier: Programming Language :: Python :: 2.6
Classifier: Programming Language :: Python :: 2.7
Classifier: Framework :: Django
